adventure/__init__.py
adventure/__main__.py
adventure/data.py
adventure/game.py
adventure/model.py
adventure/prompt.py
adventure/tests/__init__.py
adventure/tests/test_commands.py
adventure/tests/test_data.py
adventure/tests/test_walks.py
adventure_anywhere/__init__.py
adventure_anywhere/__main__.py
adventure_anywhere/definitions.py
adventure_anywhere/exceptions.py
adventure_anywhere/file_system_saves.py
adventure_anywhere/game.py
adventure_anywhere/policies.py
adventure_anywhere/s3_bucket_saves.py
adventure_anywhere/special_sms_functionality.py
adventure_anywhere/use_adventure.py
adventure_anywhere/utils.py
alexa_adventure/__init__.py
alexa_adventure/handler.py
alexa_adventure/util.py
sms_adventure/__init__.py
sms_adventure/handler.py
adventure_anywhere-1.0.1.dist-info/LICENSE.ASF-2
adventure_anywhere-1.0.1.dist-info/METADATA
adventure_anywhere-1.0.1.dist-info/WHEEL
adventure_anywhere-1.0.1.dist-info/top_level.txt
adventure_anywhere-1.0.1.dist-info/RECORD
