Metadata-Version: 2.1
Name: adventure-anywhere
Version: 1.0.1
Summary: Port of the 1977 ADVENTURE game that supports long-running sessions amongst multiple players.
Home-page: https://github.com/zhammer/adventure-anywhere
Author: Zach Hammer
Author-email: zach.the.hammer@gmail.com
License: MIT License
Platform: UNKNOWN
Requires-Dist: adventure
